boiler_plate_math/number_add.py
boiler_plate_math/number_sub.py
boiler_plate_math-0.1.0.dist-info/METADATA
boiler_plate_math-0.1.0.dist-info/WHEEL
boiler_plate_math-0.1.0.dist-info/RECORD
