Metadata-Version: 2.3
Name: boiler-plate-math
Version: 0.1.0
Summary: Boiler Plate Python Project
Author: Sganjala srilakshmi.ganjala@gmail.com
Requires-Python: >=3.11,<4.0
Classifier: Programming Language :: Python :: 3
Classifier: Programming Language :: Python :: 3.11
Classifier: Programming Language :: Python :: 3.12
Classifier: Programming Language :: Python :: 3.13
